blaxel/__init__.py
blaxel/client.py
blaxel/errors.py
blaxel/py.typed
blaxel/run.py
blaxel/types.py
blaxel/agents/__init__.py
blaxel/agents/chain.py
blaxel/agents/chat.py
blaxel/agents/decorator.py
blaxel/agents/thread.py
blaxel/agents/voice/openai.py
blaxel/agents/voice/utils.py
blaxel/api/__init__.py
blaxel/api/agents/__init__.py
blaxel/api/agents/create_agent.py
blaxel/api/agents/delete_agent.py
blaxel/api/agents/get_agent.py
blaxel/api/agents/get_agent_logs.py
blaxel/api/agents/get_agent_metrics.py
blaxel/api/agents/get_agent_trace_ids.py
blaxel/api/agents/list_agent_revisions.py
blaxel/api/agents/list_agents.py
blaxel/api/agents/update_agent.py
blaxel/api/configurations/__init__.py
blaxel/api/configurations/get_configuration.py
blaxel/api/default/__init__.py
blaxel/api/default/get_trace.py
blaxel/api/default/get_trace_ids.py
blaxel/api/default/get_trace_logs.py
blaxel/api/default/list_mcp_hub_definitions.py
blaxel/api/functions/__init__.py
blaxel/api/functions/create_function.py
blaxel/api/functions/delete_function.py
blaxel/api/functions/get_function.py
blaxel/api/functions/get_function_logs.py
blaxel/api/functions/get_function_metrics.py
blaxel/api/functions/get_function_trace_ids.py
blaxel/api/functions/list_function_revisions.py
blaxel/api/functions/list_functions.py
blaxel/api/functions/update_function.py
blaxel/api/integrations/__init__.py
blaxel/api/integrations/create_integration_connection.py
blaxel/api/integrations/delete_integration_connection.py
blaxel/api/integrations/get_integration.py
blaxel/api/integrations/get_integration_connection.py
blaxel/api/integrations/get_integration_connection_model.py
blaxel/api/integrations/get_integration_connection_model_endpoint_configurations.py
blaxel/api/integrations/list_integration_connection_models.py
blaxel/api/integrations/list_integration_connections.py
blaxel/api/integrations/update_integration_connection.py
blaxel/api/invitations/__init__.py
blaxel/api/invitations/list_all_pending_invitations.py
blaxel-0.64.0.dist-info/METADATA
blaxel-0.64.0.dist-info/WHEEL
blaxel-0.64.0.dist-info/entry_points.txt
blaxel-0.64.0.dist-info/licenses/LICENSE
blaxel-0.64.0.dist-info/RECORD
