Metadata-Version: 2.4
Name: blaxel
Version: 0.64.0
Summary: Add your description here
Author-email: cploujoux <ch.ploujoux@gmail.com>
License-File: LICENSE
Requires-Python: >=3.12
Requires-Dist: asgi-correlation-id<5.0.0,>=4.3.4
Requires-Dist: attrs>=21.3.0
Requires-Dist: fastapi[standard]<0.116.0,>=0.115.4
Requires-Dist: httpx<0.28.0,>=0.20.0
Requires-Dist: langchain-community<0.4.0,>=0.3.3
Requires-Dist: langchain-core<0.4.0,>=0.3.13
Requires-Dist: langgraph<0.3.0,>=0.2.40
Requires-Dist: mcp>=1.2.1
Requires-Dist: opentelemetry-api>=1.28.2
Requires-Dist: opentelemetry-exporter-otlp>=1.28.2
Requires-Dist: opentelemetry-instrumentation-anthropic>=0.35.0
Requires-Dist: opentelemetry-instrumentation-chromadb>=0.35.0
Requires-Dist: opentelemetry-instrumentation-cohere>=0.35.0
Requires-Dist: opentelemetry-instrumentation-fastapi>=0.49b2
Requires-Dist: opentelemetry-instrumentation-groq>=0.35.0
Requires-Dist: opentelemetry-instrumentation-httpx>=0.49b2
Requires-Dist: opentelemetry-instrumentation-lancedb>=0.35.0
Requires-Dist: opentelemetry-instrumentation-langchain>=0.35.0
Requires-Dist: opentelemetry-instrumentation-llamaindex>=0.35.0
Requires-Dist: opentelemetry-instrumentation-marqo>=0.35.0
Requires-Dist: opentelemetry-instrumentation-milvus>=0.35.0
Requires-Dist: opentelemetry-instrumentation-mistralai>=0.35.0
Requires-Dist: opentelemetry-instrumentation-ollama>=0.35.0
Requires-Dist: opentelemetry-instrumentation-openai>=0.35.0
Requires-Dist: opentelemetry-instrumentation-pinecone>=0.35.0
Requires-Dist: opentelemetry-instrumentation-qdrant>=0.35.0
Requires-Dist: opentelemetry-instrumentation-replicate>=0.35.0
Requires-Dist: opentelemetry-instrumentation-system-metrics>=0.50b0
Requires-Dist: opentelemetry-instrumentation-together>=0.35.0
Requires-Dist: opentelemetry-instrumentation-watsonx>=0.35.0
Requires-Dist: opentelemetry-instrumentation-weaviate>=0.35.0
Requires-Dist: opentelemetry-sdk>=1.28.2
Requires-Dist: pydantic-settings<2.7.0,>=2.6.1
Requires-Dist: pydantic<2.11.0,>=2.10.3
Requires-Dist: pyjwt>=2.10.1
Requires-Dist: python-dateutil>=2.8.0
Requires-Dist: pyyaml<6.1.0,>=6.0.2
Requires-Dist: requests<2.33.0,>=2.32.3
Requires-Dist: websocket>=0.2.1
Requires-Dist: websockets>=14.1
